__init__.py
frm/__init__.py
frm/instruments/__init__.py
frm/instruments/fx/__init__.py
frm/instruments/fx/option.py
frm/instruments/fx/option_multicore.py
frm/instruments/fx/Archive/heston_matlab_to_python.py
frm/instruments/fx/Archive/heston_matlab_to_python_translation.py
frm/instruments/fx/Archive/hoston_janek_agnieska_converted_to_python.py
frm/instruments/ir/__init__.py
frm/instruments/ir/caplet.py
frm/instruments/ir/interest_rate_forwards.py
frm/instruments/ir/leg.py
frm/instruments/ir/money_market.py
frm/instruments/ir/swap.py
frm/instruments/ir/swap_defaults.py
frm/instruments/ir/write_cashflow_to_excel.py
frm/instruments/ir/yieldCurve bond yield.py
frm/instruments/paused/bond.py
frm/market_data/__init__.py
frm/market_data/fx_volatility_surface.py
frm/market_data/iban_ccys.py
frm/market_data/ir_zero_curve.py
frm/pricing_engine/garman_kohlhagen.py
frm/pricing_engine/gbm.py
frm/pricing_engine/heston.py
frm/pricing_engine/heston_gk.py
frm/pricing_engine/archive/AllFunctions.py
frm/pricing_engine/archive/OptionPricing.py
frm/pricing_engine/archive/garman_kohlhagen_original.py
frm/pricing_engine/archive/garman_kohlhagen_v1.py
frm/pricing_engine/archive/heston.py
frm/pricing_engine/archive/heston_COS.py
frm/pricing_engine/archive/heston_COS_cleaned.py
frm/pricing_engine/archive/heston_COS_cleaned_.py
frm/pricing_engine/archive/heston_COS_cleaned_2.py
frm/pricing_engine/archive/sim_heston.py
frm/pricing_engine/in_progress/vanna_volga_forked.py
frm/pricing_engine/in_progress/vanna_volga_own.py
frm/pricing_engine/in_progress/vannavolga.py
frm/schedule/__init__.py
frm/schedule/business_day_calendar.py
frm/schedule/calendar.py
frm/schedule/daycounter.py
frm/schedule/schedule.py
frm/schedule/tenor.py
frm/schedule/utilities.py
frm_shasa-0.0.1.dist-info/METADATA
frm_shasa-0.0.1.dist-info/WHEEL
frm_shasa-0.0.1.dist-info/licenses/LICENSE
frm_shasa-0.0.1.dist-info/RECORD
