Metadata-Version: 2.1
Name: frm_shasa
Version: 0.0.1
Summary: A python package for quantitative finance and derivative pricing
Project-URL: Homepage, https://github.com/shasafoster/frm
Project-URL: Website, https://www.frmcalcs.com/app_frm/
Author-email: Shasa Foster   <shasa.foster.frm@gmail.com>
License-File: LICENSE
Classifier: License :: OSI Approved :: Mozilla Public License 2.0 (MPL 2.0)
Classifier: Operating System :: OS Independent
Classifier: Programming Language :: Python :: 3
Requires-Python: >=3.10
Requires-Dist: datetime
Requires-Dist: holidays
Requires-Dist: matplotlib
Requires-Dist: numba
Requires-Dist: numpy
Requires-Dist: pandas
Requires-Dist: pandas-market-calendars
Requires-Dist: scipy
